<queries>

<aQuery><region name="Global" /><supplyDemandQuery title="outputs by subsector">
                <axis1 name="sector">sector[@name]</axis1>
                <axis2 name="Year">physical-output[@vintage]</axis2>
                <xPath buildList="true" dataName="output" group="false" sumAll="false">*[@type='sector']/*[@type='subsector']//*[@type='output']/physical-output/node()</xPath>
                <comments />
            </supplyDemandQuery>
            </aQuery><aQuery><region name="USA" /><supplyDemandQuery title="outputs by subsector">
                <axis1 name="sector">sector[@name]</axis1>
                <axis2 name="Year">physical-output[@vintage]</axis2>
                <xPath buildList="true" dataName="output" group="false" sumAll="false">*[@type='sector']/*[@type='subsector']//*[@type='output']/physical-output/node()</xPath>
                <comments />
            </supplyDemandQuery>
            </aQuery><aQuery><region name="Africa_Eastern" /><supplyDemandQuery title="outputs by subsector">
                <axis1 name="sector">sector[@name]</axis1>
                <axis2 name="Year">physical-output[@vintage]</axis2>
                <xPath buildList="true" dataName="output" group="false" sumAll="false">*[@type='sector']/*[@type='subsector']//*[@type='output']/physical-output/node()</xPath>
                <comments />
            </supplyDemandQuery>
            </aQuery><aQuery><region name="Africa_Northern" /><supplyDemandQuery title="outputs by subsector">
                <axis1 name="sector">sector[@name]</axis1>
                <axis2 name="Year">physical-output[@vintage]</axis2>
                <xPath buildList="true" dataName="output" group="false" sumAll="false">*[@type='sector']/*[@type='subsector']//*[@type='output']/physical-output/node()</xPath>
                <comments />
            </supplyDemandQuery>
            </aQuery><aQuery><region name="Africa_Southern" /><supplyDemandQuery title="outputs by subsector">
                <axis1 name="sector">sector[@name]</axis1>
                <axis2 name="Year">physical-output[@vintage]</axis2>
                <xPath buildList="true" dataName="output" group="false" sumAll="false">*[@type='sector']/*[@type='subsector']//*[@type='output']/physical-output/node()</xPath>
                <comments />
            </supplyDemandQuery>
            </aQuery><aQuery><region name="Africa_Western" /><supplyDemandQuery title="outputs by subsector">
                <axis1 name="sector">sector[@name]</axis1>
                <axis2 name="Year">physical-output[@vintage]</axis2>
                <xPath buildList="true" dataName="output" group="false" sumAll="false">*[@type='sector']/*[@type='subsector']//*[@type='output']/physical-output/node()</xPath>
                <comments />
            </supplyDemandQuery>
            </aQuery><aQuery><region name="Australia_NZ" /><supplyDemandQuery title="outputs by subsector">
                <axis1 name="sector">sector[@name]</axis1>
                <axis2 name="Year">physical-output[@vintage]</axis2>
                <xPath buildList="true" dataName="output" group="false" sumAll="false">*[@type='sector']/*[@type='subsector']//*[@type='output']/physical-output/node()</xPath>
                <comments />
            </supplyDemandQuery>
            </aQuery><aQuery><region name="Brazil" /><supplyDemandQuery title="outputs by subsector">
                <axis1 name="sector">sector[@name]</axis1>
                <axis2 name="Year">physical-output[@vintage]</axis2>
                <xPath buildList="true" dataName="output" group="false" sumAll="false">*[@type='sector']/*[@type='subsector']//*[@type='output']/physical-output/node()</xPath>
                <comments />
            </supplyDemandQuery>
            </aQuery><aQuery><region name="Canada" /><supplyDemandQuery title="outputs by subsector">
                <axis1 name="sector">sector[@name]</axis1>
                <axis2 name="Year">physical-output[@vintage]</axis2>
                <xPath buildList="true" dataName="output" group="false" sumAll="false">*[@type='sector']/*[@type='subsector']//*[@type='output']/physical-output/node()</xPath>
                <comments />
            </supplyDemandQuery>
            </aQuery><aQuery><region name="Central America and Caribbean" /><supplyDemandQuery title="outputs by subsector">
                <axis1 name="sector">sector[@name]</axis1>
                <axis2 name="Year">physical-output[@vintage]</axis2>
                <xPath buildList="true" dataName="output" group="false" sumAll="false">*[@type='sector']/*[@type='subsector']//*[@type='output']/physical-output/node()</xPath>
                <comments />
            </supplyDemandQuery>
            </aQuery><aQuery><region name="Central Asia" /><supplyDemandQuery title="outputs by subsector">
                <axis1 name="sector">sector[@name]</axis1>
                <axis2 name="Year">physical-output[@vintage]</axis2>
                <xPath buildList="true" dataName="output" group="false" sumAll="false">*[@type='sector']/*[@type='subsector']//*[@type='output']/physical-output/node()</xPath>
                <comments />
            </supplyDemandQuery>
            </aQuery><aQuery><region name="China" /><supplyDemandQuery title="outputs by subsector">
                <axis1 name="sector">sector[@name]</axis1>
                <axis2 name="Year">physical-output[@vintage]</axis2>
                <xPath buildList="true" dataName="output" group="false" sumAll="false">*[@type='sector']/*[@type='subsector']//*[@type='output']/physical-output/node()</xPath>
                <comments />
            </supplyDemandQuery>
            </aQuery><aQuery><region name="EU-12" /><supplyDemandQuery title="outputs by subsector">
                <axis1 name="sector">sector[@name]</axis1>
                <axis2 name="Year">physical-output[@vintage]</axis2>
                <xPath buildList="true" dataName="output" group="false" sumAll="false">*[@type='sector']/*[@type='subsector']//*[@type='output']/physical-output/node()</xPath>
                <comments />
            </supplyDemandQuery>
            </aQuery><aQuery><region name="EU-15" /><supplyDemandQuery title="outputs by subsector">
                <axis1 name="sector">sector[@name]</axis1>
                <axis2 name="Year">physical-output[@vintage]</axis2>
                <xPath buildList="true" dataName="output" group="false" sumAll="false">*[@type='sector']/*[@type='subsector']//*[@type='output']/physical-output/node()</xPath>
                <comments />
            </supplyDemandQuery>
            </aQuery><aQuery><region name="Europe_Eastern" /><supplyDemandQuery title="outputs by subsector">
                <axis1 name="sector">sector[@name]</axis1>
                <axis2 name="Year">physical-output[@vintage]</axis2>
                <xPath buildList="true" dataName="output" group="false" sumAll="false">*[@type='sector']/*[@type='subsector']//*[@type='output']/physical-output/node()</xPath>
                <comments />
            </supplyDemandQuery>
            </aQuery><aQuery><region name="Europe_Non_EU" /><supplyDemandQuery title="outputs by subsector">
                <axis1 name="sector">sector[@name]</axis1>
                <axis2 name="Year">physical-output[@vintage]</axis2>
                <xPath buildList="true" dataName="output" group="false" sumAll="false">*[@type='sector']/*[@type='subsector']//*[@type='output']/physical-output/node()</xPath>
                <comments />
            </supplyDemandQuery>
            </aQuery><aQuery><region name="European Free Trade Association" /><supplyDemandQuery title="outputs by subsector">
                <axis1 name="sector">sector[@name]</axis1>
                <axis2 name="Year">physical-output[@vintage]</axis2>
                <xPath buildList="true" dataName="output" group="false" sumAll="false">*[@type='sector']/*[@type='subsector']//*[@type='output']/physical-output/node()</xPath>
                <comments />
            </supplyDemandQuery>
            </aQuery><aQuery><region name="India" /><supplyDemandQuery title="outputs by subsector">
                <axis1 name="sector">sector[@name]</axis1>
                <axis2 name="Year">physical-output[@vintage]</axis2>
                <xPath buildList="true" dataName="output" group="false" sumAll="false">*[@type='sector']/*[@type='subsector']//*[@type='output']/physical-output/node()</xPath>
                <comments />
            </supplyDemandQuery>
            </aQuery><aQuery><region name="Indonesia" /><supplyDemandQuery title="outputs by subsector">
                <axis1 name="sector">sector[@name]</axis1>
                <axis2 name="Year">physical-output[@vintage]</axis2>
                <xPath buildList="true" dataName="output" group="false" sumAll="false">*[@type='sector']/*[@type='subsector']//*[@type='output']/physical-output/node()</xPath>
                <comments />
            </supplyDemandQuery>
            </aQuery><aQuery><region name="Japan" /><supplyDemandQuery title="outputs by subsector">
                <axis1 name="sector">sector[@name]</axis1>
                <axis2 name="Year">physical-output[@vintage]</axis2>
                <xPath buildList="true" dataName="output" group="false" sumAll="false">*[@type='sector']/*[@type='subsector']//*[@type='output']/physical-output/node()</xPath>
                <comments />
            </supplyDemandQuery>
            </aQuery><aQuery><region name="Mexico" /><supplyDemandQuery title="outputs by subsector">
                <axis1 name="sector">sector[@name]</axis1>
                <axis2 name="Year">physical-output[@vintage]</axis2>
                <xPath buildList="true" dataName="output" group="false" sumAll="false">*[@type='sector']/*[@type='subsector']//*[@type='output']/physical-output/node()</xPath>
                <comments />
            </supplyDemandQuery>
            </aQuery><aQuery><region name="Middle East" /><supplyDemandQuery title="outputs by subsector">
                <axis1 name="sector">sector[@name]</axis1>
                <axis2 name="Year">physical-output[@vintage]</axis2>
                <xPath buildList="true" dataName="output" group="false" sumAll="false">*[@type='sector']/*[@type='subsector']//*[@type='output']/physical-output/node()</xPath>
                <comments />
            </supplyDemandQuery>
            </aQuery><aQuery><region name="Pakistan" /><supplyDemandQuery title="outputs by subsector">
                <axis1 name="sector">sector[@name]</axis1>
                <axis2 name="Year">physical-output[@vintage]</axis2>
                <xPath buildList="true" dataName="output" group="false" sumAll="false">*[@type='sector']/*[@type='subsector']//*[@type='output']/physical-output/node()</xPath>
                <comments />
            </supplyDemandQuery>
            </aQuery><aQuery><region name="Russia" /><supplyDemandQuery title="outputs by subsector">
                <axis1 name="sector">sector[@name]</axis1>
                <axis2 name="Year">physical-output[@vintage]</axis2>
                <xPath buildList="true" dataName="output" group="false" sumAll="false">*[@type='sector']/*[@type='subsector']//*[@type='output']/physical-output/node()</xPath>
                <comments />
            </supplyDemandQuery>
            </aQuery><aQuery><region name="South Africa" /><supplyDemandQuery title="outputs by subsector">
                <axis1 name="sector">sector[@name]</axis1>
                <axis2 name="Year">physical-output[@vintage]</axis2>
                <xPath buildList="true" dataName="output" group="false" sumAll="false">*[@type='sector']/*[@type='subsector']//*[@type='output']/physical-output/node()</xPath>
                <comments />
            </supplyDemandQuery>
            </aQuery><aQuery><region name="South America_Northern" /><supplyDemandQuery title="outputs by subsector">
                <axis1 name="sector">sector[@name]</axis1>
                <axis2 name="Year">physical-output[@vintage]</axis2>
                <xPath buildList="true" dataName="output" group="false" sumAll="false">*[@type='sector']/*[@type='subsector']//*[@type='output']/physical-output/node()</xPath>
                <comments />
            </supplyDemandQuery>
            </aQuery><aQuery><region name="South America_Southern" /><supplyDemandQuery title="outputs by subsector">
                <axis1 name="sector">sector[@name]</axis1>
                <axis2 name="Year">physical-output[@vintage]</axis2>
                <xPath buildList="true" dataName="output" group="false" sumAll="false">*[@type='sector']/*[@type='subsector']//*[@type='output']/physical-output/node()</xPath>
                <comments />
            </supplyDemandQuery>
            </aQuery><aQuery><region name="South Asia" /><supplyDemandQuery title="outputs by subsector">
                <axis1 name="sector">sector[@name]</axis1>
                <axis2 name="Year">physical-output[@vintage]</axis2>
                <xPath buildList="true" dataName="output" group="false" sumAll="false">*[@type='sector']/*[@type='subsector']//*[@type='output']/physical-output/node()</xPath>
                <comments />
            </supplyDemandQuery>
            </aQuery><aQuery><region name="South Korea" /><supplyDemandQuery title="outputs by subsector">
                <axis1 name="sector">sector[@name]</axis1>
                <axis2 name="Year">physical-output[@vintage]</axis2>
                <xPath buildList="true" dataName="output" group="false" sumAll="false">*[@type='sector']/*[@type='subsector']//*[@type='output']/physical-output/node()</xPath>
                <comments />
            </supplyDemandQuery>
            </aQuery><aQuery><region name="Southeast Asia" /><supplyDemandQuery title="outputs by subsector">
                <axis1 name="sector">sector[@name]</axis1>
                <axis2 name="Year">physical-output[@vintage]</axis2>
                <xPath buildList="true" dataName="output" group="false" sumAll="false">*[@type='sector']/*[@type='subsector']//*[@type='output']/physical-output/node()</xPath>
                <comments />
            </supplyDemandQuery>
            </aQuery><aQuery><region name="Taiwan" /><supplyDemandQuery title="outputs by subsector">
                <axis1 name="sector">sector[@name]</axis1>
                <axis2 name="Year">physical-output[@vintage]</axis2>
                <xPath buildList="true" dataName="output" group="false" sumAll="false">*[@type='sector']/*[@type='subsector']//*[@type='output']/physical-output/node()</xPath>
                <comments />
            </supplyDemandQuery>
            </aQuery><aQuery><region name="Argentina" /><supplyDemandQuery title="outputs by subsector">
                <axis1 name="sector">sector[@name]</axis1>
                <axis2 name="Year">physical-output[@vintage]</axis2>
                <xPath buildList="true" dataName="output" group="false" sumAll="false">*[@type='sector']/*[@type='subsector']//*[@type='output']/physical-output/node()</xPath>
                <comments />
            </supplyDemandQuery>
            </aQuery><aQuery><region name="Colombia" /><supplyDemandQuery title="outputs by subsector">
                <axis1 name="sector">sector[@name]</axis1>
                <axis2 name="Year">physical-output[@vintage]</axis2>
                <xPath buildList="true" dataName="output" group="false" sumAll="false">*[@type='sector']/*[@type='subsector']//*[@type='output']/physical-output/node()</xPath>
                <comments />
            </supplyDemandQuery>
            </aQuery></queries>