<queries>

<aQuery><region name="Global" /><costCurveQuery title="undiscounted policy cost">
         <axis1 name="UndiscountedCost">UndiscountedCost</axis1>
         <axis2 name="region">UndiscountedCost</axis2>
         <xPath buildList="true" dataName="Undiscounted Cost" group="false" sumAll="false">/text()</xPath>
         <comments />
      </costCurveQuery>
      </aQuery><aQuery><region name="AK" /><costCurveQuery title="undiscounted policy cost">
         <axis1 name="UndiscountedCost">UndiscountedCost</axis1>
         <axis2 name="region">UndiscountedCost</axis2>
         <xPath buildList="true" dataName="Undiscounted Cost" group="false" sumAll="false">/text()</xPath>
         <comments />
      </costCurveQuery>
      </aQuery><aQuery><region name="AL" /><costCurveQuery title="undiscounted policy cost">
         <axis1 name="UndiscountedCost">UndiscountedCost</axis1>
         <axis2 name="region">UndiscountedCost</axis2>
         <xPath buildList="true" dataName="Undiscounted Cost" group="false" sumAll="false">/text()</xPath>
         <comments />
      </costCurveQuery>
      </aQuery><aQuery><region name="AR" /><costCurveQuery title="undiscounted policy cost">
         <axis1 name="UndiscountedCost">UndiscountedCost</axis1>
         <axis2 name="region">UndiscountedCost</axis2>
         <xPath buildList="true" dataName="Undiscounted Cost" group="false" sumAll="false">/text()</xPath>
         <comments />
      </costCurveQuery>
      </aQuery><aQuery><region name="AZ" /><costCurveQuery title="undiscounted policy cost">
         <axis1 name="UndiscountedCost">UndiscountedCost</axis1>
         <axis2 name="region">UndiscountedCost</axis2>
         <xPath buildList="true" dataName="Undiscounted Cost" group="false" sumAll="false">/text()</xPath>
         <comments />
      </costCurveQuery>
      </aQuery><aQuery><region name="CA" /><costCurveQuery title="undiscounted policy cost">
         <axis1 name="UndiscountedCost">UndiscountedCost</axis1>
         <axis2 name="region">UndiscountedCost</axis2>
         <xPath buildList="true" dataName="Undiscounted Cost" group="false" sumAll="false">/text()</xPath>
         <comments />
      </costCurveQuery>
      </aQuery><aQuery><region name="CO" /><costCurveQuery title="undiscounted policy cost">
         <axis1 name="UndiscountedCost">UndiscountedCost</axis1>
         <axis2 name="region">UndiscountedCost</axis2>
         <xPath buildList="true" dataName="Undiscounted Cost" group="false" sumAll="false">/text()</xPath>
         <comments />
      </costCurveQuery>
      </aQuery><aQuery><region name="CT" /><costCurveQuery title="undiscounted policy cost">
         <axis1 name="UndiscountedCost">UndiscountedCost</axis1>
         <axis2 name="region">UndiscountedCost</axis2>
         <xPath buildList="true" dataName="Undiscounted Cost" group="false" sumAll="false">/text()</xPath>
         <comments />
      </costCurveQuery>
      </aQuery><aQuery><region name="DC" /><costCurveQuery title="undiscounted policy cost">
         <axis1 name="UndiscountedCost">UndiscountedCost</axis1>
         <axis2 name="region">UndiscountedCost</axis2>
         <xPath buildList="true" dataName="Undiscounted Cost" group="false" sumAll="false">/text()</xPath>
         <comments />
      </costCurveQuery>
      </aQuery><aQuery><region name="DE" /><costCurveQuery title="undiscounted policy cost">
         <axis1 name="UndiscountedCost">UndiscountedCost</axis1>
         <axis2 name="region">UndiscountedCost</axis2>
         <xPath buildList="true" dataName="Undiscounted Cost" group="false" sumAll="false">/text()</xPath>
         <comments />
      </costCurveQuery>
      </aQuery><aQuery><region name="FL" /><costCurveQuery title="undiscounted policy cost">
         <axis1 name="UndiscountedCost">UndiscountedCost</axis1>
         <axis2 name="region">UndiscountedCost</axis2>
         <xPath buildList="true" dataName="Undiscounted Cost" group="false" sumAll="false">/text()</xPath>
         <comments />
      </costCurveQuery>
      </aQuery><aQuery><region name="GA" /><costCurveQuery title="undiscounted policy cost">
         <axis1 name="UndiscountedCost">UndiscountedCost</axis1>
         <axis2 name="region">UndiscountedCost</axis2>
         <xPath buildList="true" dataName="Undiscounted Cost" group="false" sumAll="false">/text()</xPath>
         <comments />
      </costCurveQuery>
      </aQuery><aQuery><region name="HI" /><costCurveQuery title="undiscounted policy cost">
         <axis1 name="UndiscountedCost">UndiscountedCost</axis1>
         <axis2 name="region">UndiscountedCost</axis2>
         <xPath buildList="true" dataName="Undiscounted Cost" group="false" sumAll="false">/text()</xPath>
         <comments />
      </costCurveQuery>
      </aQuery><aQuery><region name="IA" /><costCurveQuery title="undiscounted policy cost">
         <axis1 name="UndiscountedCost">UndiscountedCost</axis1>
         <axis2 name="region">UndiscountedCost</axis2>
         <xPath buildList="true" dataName="Undiscounted Cost" group="false" sumAll="false">/text()</xPath>
         <comments />
      </costCurveQuery>
      </aQuery><aQuery><region name="ID" /><costCurveQuery title="undiscounted policy cost">
         <axis1 name="UndiscountedCost">UndiscountedCost</axis1>
         <axis2 name="region">UndiscountedCost</axis2>
         <xPath buildList="true" dataName="Undiscounted Cost" group="false" sumAll="false">/text()</xPath>
         <comments />
      </costCurveQuery>
      </aQuery><aQuery><region name="IL" /><costCurveQuery title="undiscounted policy cost">
         <axis1 name="UndiscountedCost">UndiscountedCost</axis1>
         <axis2 name="region">UndiscountedCost</axis2>
         <xPath buildList="true" dataName="Undiscounted Cost" group="false" sumAll="false">/text()</xPath>
         <comments />
      </costCurveQuery>
      </aQuery><aQuery><region name="IN" /><costCurveQuery title="undiscounted policy cost">
         <axis1 name="UndiscountedCost">UndiscountedCost</axis1>
         <axis2 name="region">UndiscountedCost</axis2>
         <xPath buildList="true" dataName="Undiscounted Cost" group="false" sumAll="false">/text()</xPath>
         <comments />
      </costCurveQuery>
      </aQuery><aQuery><region name="KS" /><costCurveQuery title="undiscounted policy cost">
         <axis1 name="UndiscountedCost">UndiscountedCost</axis1>
         <axis2 name="region">UndiscountedCost</axis2>
         <xPath buildList="true" dataName="Undiscounted Cost" group="false" sumAll="false">/text()</xPath>
         <comments />
      </costCurveQuery>
      </aQuery><aQuery><region name="KY" /><costCurveQuery title="undiscounted policy cost">
         <axis1 name="UndiscountedCost">UndiscountedCost</axis1>
         <axis2 name="region">UndiscountedCost</axis2>
         <xPath buildList="true" dataName="Undiscounted Cost" group="false" sumAll="false">/text()</xPath>
         <comments />
      </costCurveQuery>
      </aQuery><aQuery><region name="LA" /><costCurveQuery title="undiscounted policy cost">
         <axis1 name="UndiscountedCost">UndiscountedCost</axis1>
         <axis2 name="region">UndiscountedCost</axis2>
         <xPath buildList="true" dataName="Undiscounted Cost" group="false" sumAll="false">/text()</xPath>
         <comments />
      </costCurveQuery>
      </aQuery><aQuery><region name="MA" /><costCurveQuery title="undiscounted policy cost">
         <axis1 name="UndiscountedCost">UndiscountedCost</axis1>
         <axis2 name="region">UndiscountedCost</axis2>
         <xPath buildList="true" dataName="Undiscounted Cost" group="false" sumAll="false">/text()</xPath>
         <comments />
      </costCurveQuery>
      </aQuery><aQuery><region name="MD" /><costCurveQuery title="undiscounted policy cost">
         <axis1 name="UndiscountedCost">UndiscountedCost</axis1>
         <axis2 name="region">UndiscountedCost</axis2>
         <xPath buildList="true" dataName="Undiscounted Cost" group="false" sumAll="false">/text()</xPath>
         <comments />
      </costCurveQuery>
      </aQuery><aQuery><region name="ME" /><costCurveQuery title="undiscounted policy cost">
         <axis1 name="UndiscountedCost">UndiscountedCost</axis1>
         <axis2 name="region">UndiscountedCost</axis2>
         <xPath buildList="true" dataName="Undiscounted Cost" group="false" sumAll="false">/text()</xPath>
         <comments />
      </costCurveQuery>
      </aQuery><aQuery><region name="MI" /><costCurveQuery title="undiscounted policy cost">
         <axis1 name="UndiscountedCost">UndiscountedCost</axis1>
         <axis2 name="region">UndiscountedCost</axis2>
         <xPath buildList="true" dataName="Undiscounted Cost" group="false" sumAll="false">/text()</xPath>
         <comments />
      </costCurveQuery>
      </aQuery><aQuery><region name="MN" /><costCurveQuery title="undiscounted policy cost">
         <axis1 name="UndiscountedCost">UndiscountedCost</axis1>
         <axis2 name="region">UndiscountedCost</axis2>
         <xPath buildList="true" dataName="Undiscounted Cost" group="false" sumAll="false">/text()</xPath>
         <comments />
      </costCurveQuery>
      </aQuery><aQuery><region name="MO" /><costCurveQuery title="undiscounted policy cost">
         <axis1 name="UndiscountedCost">UndiscountedCost</axis1>
         <axis2 name="region">UndiscountedCost</axis2>
         <xPath buildList="true" dataName="Undiscounted Cost" group="false" sumAll="false">/text()</xPath>
         <comments />
      </costCurveQuery>
      </aQuery><aQuery><region name="MS" /><costCurveQuery title="undiscounted policy cost">
         <axis1 name="UndiscountedCost">UndiscountedCost</axis1>
         <axis2 name="region">UndiscountedCost</axis2>
         <xPath buildList="true" dataName="Undiscounted Cost" group="false" sumAll="false">/text()</xPath>
         <comments />
      </costCurveQuery>
      </aQuery><aQuery><region name="MT" /><costCurveQuery title="undiscounted policy cost">
         <axis1 name="UndiscountedCost">UndiscountedCost</axis1>
         <axis2 name="region">UndiscountedCost</axis2>
         <xPath buildList="true" dataName="Undiscounted Cost" group="false" sumAll="false">/text()</xPath>
         <comments />
      </costCurveQuery>
      </aQuery><aQuery><region name="NC" /><costCurveQuery title="undiscounted policy cost">
         <axis1 name="UndiscountedCost">UndiscountedCost</axis1>
         <axis2 name="region">UndiscountedCost</axis2>
         <xPath buildList="true" dataName="Undiscounted Cost" group="false" sumAll="false">/text()</xPath>
         <comments />
      </costCurveQuery>
      </aQuery><aQuery><region name="ND" /><costCurveQuery title="undiscounted policy cost">
         <axis1 name="UndiscountedCost">UndiscountedCost</axis1>
         <axis2 name="region">UndiscountedCost</axis2>
         <xPath buildList="true" dataName="Undiscounted Cost" group="false" sumAll="false">/text()</xPath>
         <comments />
      </costCurveQuery>
      </aQuery><aQuery><region name="NE" /><costCurveQuery title="undiscounted policy cost">
         <axis1 name="UndiscountedCost">UndiscountedCost</axis1>
         <axis2 name="region">UndiscountedCost</axis2>
         <xPath buildList="true" dataName="Undiscounted Cost" group="false" sumAll="false">/text()</xPath>
         <comments />
      </costCurveQuery>
      </aQuery><aQuery><region name="NH" /><costCurveQuery title="undiscounted policy cost">
         <axis1 name="UndiscountedCost">UndiscountedCost</axis1>
         <axis2 name="region">UndiscountedCost</axis2>
         <xPath buildList="true" dataName="Undiscounted Cost" group="false" sumAll="false">/text()</xPath>
         <comments />
      </costCurveQuery>
      </aQuery><aQuery><region name="NJ" /><costCurveQuery title="undiscounted policy cost">
         <axis1 name="UndiscountedCost">UndiscountedCost</axis1>
         <axis2 name="region">UndiscountedCost</axis2>
         <xPath buildList="true" dataName="Undiscounted Cost" group="false" sumAll="false">/text()</xPath>
         <comments />
      </costCurveQuery>
      </aQuery><aQuery><region name="NM" /><costCurveQuery title="undiscounted policy cost">
         <axis1 name="UndiscountedCost">UndiscountedCost</axis1>
         <axis2 name="region">UndiscountedCost</axis2>
         <xPath buildList="true" dataName="Undiscounted Cost" group="false" sumAll="false">/text()</xPath>
         <comments />
      </costCurveQuery>
      </aQuery><aQuery><region name="NV" /><costCurveQuery title="undiscounted policy cost">
         <axis1 name="UndiscountedCost">UndiscountedCost</axis1>
         <axis2 name="region">UndiscountedCost</axis2>
         <xPath buildList="true" dataName="Undiscounted Cost" group="false" sumAll="false">/text()</xPath>
         <comments />
      </costCurveQuery>
      </aQuery><aQuery><region name="NY" /><costCurveQuery title="undiscounted policy cost">
         <axis1 name="UndiscountedCost">UndiscountedCost</axis1>
         <axis2 name="region">UndiscountedCost</axis2>
         <xPath buildList="true" dataName="Undiscounted Cost" group="false" sumAll="false">/text()</xPath>
         <comments />
      </costCurveQuery>
      </aQuery><aQuery><region name="OH" /><costCurveQuery title="undiscounted policy cost">
         <axis1 name="UndiscountedCost">UndiscountedCost</axis1>
         <axis2 name="region">UndiscountedCost</axis2>
         <xPath buildList="true" dataName="Undiscounted Cost" group="false" sumAll="false">/text()</xPath>
         <comments />
      </costCurveQuery>
      </aQuery><aQuery><region name="OK" /><costCurveQuery title="undiscounted policy cost">
         <axis1 name="UndiscountedCost">UndiscountedCost</axis1>
         <axis2 name="region">UndiscountedCost</axis2>
         <xPath buildList="true" dataName="Undiscounted Cost" group="false" sumAll="false">/text()</xPath>
         <comments />
      </costCurveQuery>
      </aQuery><aQuery><region name="OR" /><costCurveQuery title="undiscounted policy cost">
         <axis1 name="UndiscountedCost">UndiscountedCost</axis1>
         <axis2 name="region">UndiscountedCost</axis2>
         <xPath buildList="true" dataName="Undiscounted Cost" group="false" sumAll="false">/text()</xPath>
         <comments />
      </costCurveQuery>
      </aQuery><aQuery><region name="PA" /><costCurveQuery title="undiscounted policy cost">
         <axis1 name="UndiscountedCost">UndiscountedCost</axis1>
         <axis2 name="region">UndiscountedCost</axis2>
         <xPath buildList="true" dataName="Undiscounted Cost" group="false" sumAll="false">/text()</xPath>
         <comments />
      </costCurveQuery>
      </aQuery><aQuery><region name="RI" /><costCurveQuery title="undiscounted policy cost">
         <axis1 name="UndiscountedCost">UndiscountedCost</axis1>
         <axis2 name="region">UndiscountedCost</axis2>
         <xPath buildList="true" dataName="Undiscounted Cost" group="false" sumAll="false">/text()</xPath>
         <comments />
      </costCurveQuery>
      </aQuery><aQuery><region name="SC" /><costCurveQuery title="undiscounted policy cost">
         <axis1 name="UndiscountedCost">UndiscountedCost</axis1>
         <axis2 name="region">UndiscountedCost</axis2>
         <xPath buildList="true" dataName="Undiscounted Cost" group="false" sumAll="false">/text()</xPath>
         <comments />
      </costCurveQuery>
      </aQuery><aQuery><region name="SD" /><costCurveQuery title="undiscounted policy cost">
         <axis1 name="UndiscountedCost">UndiscountedCost</axis1>
         <axis2 name="region">UndiscountedCost</axis2>
         <xPath buildList="true" dataName="Undiscounted Cost" group="false" sumAll="false">/text()</xPath>
         <comments />
      </costCurveQuery>
      </aQuery><aQuery><region name="TN" /><costCurveQuery title="undiscounted policy cost">
         <axis1 name="UndiscountedCost">UndiscountedCost</axis1>
         <axis2 name="region">UndiscountedCost</axis2>
         <xPath buildList="true" dataName="Undiscounted Cost" group="false" sumAll="false">/text()</xPath>
         <comments />
      </costCurveQuery>
      </aQuery><aQuery><region name="TX" /><costCurveQuery title="undiscounted policy cost">
         <axis1 name="UndiscountedCost">UndiscountedCost</axis1>
         <axis2 name="region">UndiscountedCost</axis2>
         <xPath buildList="true" dataName="Undiscounted Cost" group="false" sumAll="false">/text()</xPath>
         <comments />
      </costCurveQuery>
      </aQuery><aQuery><region name="UT" /><costCurveQuery title="undiscounted policy cost">
         <axis1 name="UndiscountedCost">UndiscountedCost</axis1>
         <axis2 name="region">UndiscountedCost</axis2>
         <xPath buildList="true" dataName="Undiscounted Cost" group="false" sumAll="false">/text()</xPath>
         <comments />
      </costCurveQuery>
      </aQuery><aQuery><region name="VA" /><costCurveQuery title="undiscounted policy cost">
         <axis1 name="UndiscountedCost">UndiscountedCost</axis1>
         <axis2 name="region">UndiscountedCost</axis2>
         <xPath buildList="true" dataName="Undiscounted Cost" group="false" sumAll="false">/text()</xPath>
         <comments />
      </costCurveQuery>
      </aQuery><aQuery><region name="VT" /><costCurveQuery title="undiscounted policy cost">
         <axis1 name="UndiscountedCost">UndiscountedCost</axis1>
         <axis2 name="region">UndiscountedCost</axis2>
         <xPath buildList="true" dataName="Undiscounted Cost" group="false" sumAll="false">/text()</xPath>
         <comments />
      </costCurveQuery>
      </aQuery><aQuery><region name="WA" /><costCurveQuery title="undiscounted policy cost">
         <axis1 name="UndiscountedCost">UndiscountedCost</axis1>
         <axis2 name="region">UndiscountedCost</axis2>
         <xPath buildList="true" dataName="Undiscounted Cost" group="false" sumAll="false">/text()</xPath>
         <comments />
      </costCurveQuery>
      </aQuery><aQuery><region name="WI" /><costCurveQuery title="undiscounted policy cost">
         <axis1 name="UndiscountedCost">UndiscountedCost</axis1>
         <axis2 name="region">UndiscountedCost</axis2>
         <xPath buildList="true" dataName="Undiscounted Cost" group="false" sumAll="false">/text()</xPath>
         <comments />
      </costCurveQuery>
      </aQuery><aQuery><region name="WV" /><costCurveQuery title="undiscounted policy cost">
         <axis1 name="UndiscountedCost">UndiscountedCost</axis1>
         <axis2 name="region">UndiscountedCost</axis2>
         <xPath buildList="true" dataName="Undiscounted Cost" group="false" sumAll="false">/text()</xPath>
         <comments />
      </costCurveQuery>
      </aQuery><aQuery><region name="WY" /><costCurveQuery title="undiscounted policy cost">
         <axis1 name="UndiscountedCost">UndiscountedCost</axis1>
         <axis2 name="region">UndiscountedCost</axis2>
         <xPath buildList="true" dataName="Undiscounted Cost" group="false" sumAll="false">/text()</xPath>
         <comments />
      </costCurveQuery>
      </aQuery><aQuery><region name="USA" /><costCurveQuery title="undiscounted policy cost">
         <axis1 name="UndiscountedCost">UndiscountedCost</axis1>
         <axis2 name="region">UndiscountedCost</axis2>
         <xPath buildList="true" dataName="Undiscounted Cost" group="false" sumAll="false">/text()</xPath>
         <comments />
      </costCurveQuery>
      </aQuery><aQuery><region name="Africa_Eastern" /><costCurveQuery title="undiscounted policy cost">
         <axis1 name="UndiscountedCost">UndiscountedCost</axis1>
         <axis2 name="region">UndiscountedCost</axis2>
         <xPath buildList="true" dataName="Undiscounted Cost" group="false" sumAll="false">/text()</xPath>
         <comments />
      </costCurveQuery>
      </aQuery><aQuery><region name="Africa_Northern" /><costCurveQuery title="undiscounted policy cost">
         <axis1 name="UndiscountedCost">UndiscountedCost</axis1>
         <axis2 name="region">UndiscountedCost</axis2>
         <xPath buildList="true" dataName="Undiscounted Cost" group="false" sumAll="false">/text()</xPath>
         <comments />
      </costCurveQuery>
      </aQuery><aQuery><region name="Africa_Southern" /><costCurveQuery title="undiscounted policy cost">
         <axis1 name="UndiscountedCost">UndiscountedCost</axis1>
         <axis2 name="region">UndiscountedCost</axis2>
         <xPath buildList="true" dataName="Undiscounted Cost" group="false" sumAll="false">/text()</xPath>
         <comments />
      </costCurveQuery>
      </aQuery><aQuery><region name="Africa_Western" /><costCurveQuery title="undiscounted policy cost">
         <axis1 name="UndiscountedCost">UndiscountedCost</axis1>
         <axis2 name="region">UndiscountedCost</axis2>
         <xPath buildList="true" dataName="Undiscounted Cost" group="false" sumAll="false">/text()</xPath>
         <comments />
      </costCurveQuery>
      </aQuery><aQuery><region name="Australia_NZ" /><costCurveQuery title="undiscounted policy cost">
         <axis1 name="UndiscountedCost">UndiscountedCost</axis1>
         <axis2 name="region">UndiscountedCost</axis2>
         <xPath buildList="true" dataName="Undiscounted Cost" group="false" sumAll="false">/text()</xPath>
         <comments />
      </costCurveQuery>
      </aQuery><aQuery><region name="Brazil" /><costCurveQuery title="undiscounted policy cost">
         <axis1 name="UndiscountedCost">UndiscountedCost</axis1>
         <axis2 name="region">UndiscountedCost</axis2>
         <xPath buildList="true" dataName="Undiscounted Cost" group="false" sumAll="false">/text()</xPath>
         <comments />
      </costCurveQuery>
      </aQuery><aQuery><region name="Canada" /><costCurveQuery title="undiscounted policy cost">
         <axis1 name="UndiscountedCost">UndiscountedCost</axis1>
         <axis2 name="region">UndiscountedCost</axis2>
         <xPath buildList="true" dataName="Undiscounted Cost" group="false" sumAll="false">/text()</xPath>
         <comments />
      </costCurveQuery>
      </aQuery><aQuery><region name="Central America and Caribbean" /><costCurveQuery title="undiscounted policy cost">
         <axis1 name="UndiscountedCost">UndiscountedCost</axis1>
         <axis2 name="region">UndiscountedCost</axis2>
         <xPath buildList="true" dataName="Undiscounted Cost" group="false" sumAll="false">/text()</xPath>
         <comments />
      </costCurveQuery>
      </aQuery><aQuery><region name="Central Asia" /><costCurveQuery title="undiscounted policy cost">
         <axis1 name="UndiscountedCost">UndiscountedCost</axis1>
         <axis2 name="region">UndiscountedCost</axis2>
         <xPath buildList="true" dataName="Undiscounted Cost" group="false" sumAll="false">/text()</xPath>
         <comments />
      </costCurveQuery>
      </aQuery><aQuery><region name="China" /><costCurveQuery title="undiscounted policy cost">
         <axis1 name="UndiscountedCost">UndiscountedCost</axis1>
         <axis2 name="region">UndiscountedCost</axis2>
         <xPath buildList="true" dataName="Undiscounted Cost" group="false" sumAll="false">/text()</xPath>
         <comments />
      </costCurveQuery>
      </aQuery><aQuery><region name="EU-12" /><costCurveQuery title="undiscounted policy cost">
         <axis1 name="UndiscountedCost">UndiscountedCost</axis1>
         <axis2 name="region">UndiscountedCost</axis2>
         <xPath buildList="true" dataName="Undiscounted Cost" group="false" sumAll="false">/text()</xPath>
         <comments />
      </costCurveQuery>
      </aQuery><aQuery><region name="EU-15" /><costCurveQuery title="undiscounted policy cost">
         <axis1 name="UndiscountedCost">UndiscountedCost</axis1>
         <axis2 name="region">UndiscountedCost</axis2>
         <xPath buildList="true" dataName="Undiscounted Cost" group="false" sumAll="false">/text()</xPath>
         <comments />
      </costCurveQuery>
      </aQuery><aQuery><region name="Europe_Eastern" /><costCurveQuery title="undiscounted policy cost">
         <axis1 name="UndiscountedCost">UndiscountedCost</axis1>
         <axis2 name="region">UndiscountedCost</axis2>
         <xPath buildList="true" dataName="Undiscounted Cost" group="false" sumAll="false">/text()</xPath>
         <comments />
      </costCurveQuery>
      </aQuery><aQuery><region name="Europe_Non_EU" /><costCurveQuery title="undiscounted policy cost">
         <axis1 name="UndiscountedCost">UndiscountedCost</axis1>
         <axis2 name="region">UndiscountedCost</axis2>
         <xPath buildList="true" dataName="Undiscounted Cost" group="false" sumAll="false">/text()</xPath>
         <comments />
      </costCurveQuery>
      </aQuery><aQuery><region name="European Free Trade Association" /><costCurveQuery title="undiscounted policy cost">
         <axis1 name="UndiscountedCost">UndiscountedCost</axis1>
         <axis2 name="region">UndiscountedCost</axis2>
         <xPath buildList="true" dataName="Undiscounted Cost" group="false" sumAll="false">/text()</xPath>
         <comments />
      </costCurveQuery>
      </aQuery><aQuery><region name="India" /><costCurveQuery title="undiscounted policy cost">
         <axis1 name="UndiscountedCost">UndiscountedCost</axis1>
         <axis2 name="region">UndiscountedCost</axis2>
         <xPath buildList="true" dataName="Undiscounted Cost" group="false" sumAll="false">/text()</xPath>
         <comments />
      </costCurveQuery>
      </aQuery><aQuery><region name="Indonesia" /><costCurveQuery title="undiscounted policy cost">
         <axis1 name="UndiscountedCost">UndiscountedCost</axis1>
         <axis2 name="region">UndiscountedCost</axis2>
         <xPath buildList="true" dataName="Undiscounted Cost" group="false" sumAll="false">/text()</xPath>
         <comments />
      </costCurveQuery>
      </aQuery><aQuery><region name="Japan" /><costCurveQuery title="undiscounted policy cost">
         <axis1 name="UndiscountedCost">UndiscountedCost</axis1>
         <axis2 name="region">UndiscountedCost</axis2>
         <xPath buildList="true" dataName="Undiscounted Cost" group="false" sumAll="false">/text()</xPath>
         <comments />
      </costCurveQuery>
      </aQuery><aQuery><region name="Mexico" /><costCurveQuery title="undiscounted policy cost">
         <axis1 name="UndiscountedCost">UndiscountedCost</axis1>
         <axis2 name="region">UndiscountedCost</axis2>
         <xPath buildList="true" dataName="Undiscounted Cost" group="false" sumAll="false">/text()</xPath>
         <comments />
      </costCurveQuery>
      </aQuery><aQuery><region name="Middle East" /><costCurveQuery title="undiscounted policy cost">
         <axis1 name="UndiscountedCost">UndiscountedCost</axis1>
         <axis2 name="region">UndiscountedCost</axis2>
         <xPath buildList="true" dataName="Undiscounted Cost" group="false" sumAll="false">/text()</xPath>
         <comments />
      </costCurveQuery>
      </aQuery><aQuery><region name="Pakistan" /><costCurveQuery title="undiscounted policy cost">
         <axis1 name="UndiscountedCost">UndiscountedCost</axis1>
         <axis2 name="region">UndiscountedCost</axis2>
         <xPath buildList="true" dataName="Undiscounted Cost" group="false" sumAll="false">/text()</xPath>
         <comments />
      </costCurveQuery>
      </aQuery><aQuery><region name="Russia" /><costCurveQuery title="undiscounted policy cost">
         <axis1 name="UndiscountedCost">UndiscountedCost</axis1>
         <axis2 name="region">UndiscountedCost</axis2>
         <xPath buildList="true" dataName="Undiscounted Cost" group="false" sumAll="false">/text()</xPath>
         <comments />
      </costCurveQuery>
      </aQuery><aQuery><region name="South Africa" /><costCurveQuery title="undiscounted policy cost">
         <axis1 name="UndiscountedCost">UndiscountedCost</axis1>
         <axis2 name="region">UndiscountedCost</axis2>
         <xPath buildList="true" dataName="Undiscounted Cost" group="false" sumAll="false">/text()</xPath>
         <comments />
      </costCurveQuery>
      </aQuery><aQuery><region name="South America_Northern" /><costCurveQuery title="undiscounted policy cost">
         <axis1 name="UndiscountedCost">UndiscountedCost</axis1>
         <axis2 name="region">UndiscountedCost</axis2>
         <xPath buildList="true" dataName="Undiscounted Cost" group="false" sumAll="false">/text()</xPath>
         <comments />
      </costCurveQuery>
      </aQuery><aQuery><region name="South America_Southern" /><costCurveQuery title="undiscounted policy cost">
         <axis1 name="UndiscountedCost">UndiscountedCost</axis1>
         <axis2 name="region">UndiscountedCost</axis2>
         <xPath buildList="true" dataName="Undiscounted Cost" group="false" sumAll="false">/text()</xPath>
         <comments />
      </costCurveQuery>
      </aQuery><aQuery><region name="South Asia" /><costCurveQuery title="undiscounted policy cost">
         <axis1 name="UndiscountedCost">UndiscountedCost</axis1>
         <axis2 name="region">UndiscountedCost</axis2>
         <xPath buildList="true" dataName="Undiscounted Cost" group="false" sumAll="false">/text()</xPath>
         <comments />
      </costCurveQuery>
      </aQuery><aQuery><region name="South Korea" /><costCurveQuery title="undiscounted policy cost">
         <axis1 name="UndiscountedCost">UndiscountedCost</axis1>
         <axis2 name="region">UndiscountedCost</axis2>
         <xPath buildList="true" dataName="Undiscounted Cost" group="false" sumAll="false">/text()</xPath>
         <comments />
      </costCurveQuery>
      </aQuery><aQuery><region name="Southeast Asia" /><costCurveQuery title="undiscounted policy cost">
         <axis1 name="UndiscountedCost">UndiscountedCost</axis1>
         <axis2 name="region">UndiscountedCost</axis2>
         <xPath buildList="true" dataName="Undiscounted Cost" group="false" sumAll="false">/text()</xPath>
         <comments />
      </costCurveQuery>
      </aQuery><aQuery><region name="Taiwan" /><costCurveQuery title="undiscounted policy cost">
         <axis1 name="UndiscountedCost">UndiscountedCost</axis1>
         <axis2 name="region">UndiscountedCost</axis2>
         <xPath buildList="true" dataName="Undiscounted Cost" group="false" sumAll="false">/text()</xPath>
         <comments />
      </costCurveQuery>
      </aQuery><aQuery><region name="Argentina" /><costCurveQuery title="undiscounted policy cost">
         <axis1 name="UndiscountedCost">UndiscountedCost</axis1>
         <axis2 name="region">UndiscountedCost</axis2>
         <xPath buildList="true" dataName="Undiscounted Cost" group="false" sumAll="false">/text()</xPath>
         <comments />
      </costCurveQuery>
      </aQuery><aQuery><region name="Colombia" /><costCurveQuery title="undiscounted policy cost">
         <axis1 name="UndiscountedCost">UndiscountedCost</axis1>
         <axis2 name="region">UndiscountedCost</axis2>
         <xPath buildList="true" dataName="Undiscounted Cost" group="false" sumAll="false">/text()</xPath>
         <comments />
      </costCurveQuery>
      </aQuery></queries>